colorex/__init__.py
colorex/colorex.py
colorex_py-0.1.5.dist-info/LICENSE
colorex_py-0.1.5.dist-info/METADATA
colorex_py-0.1.5.dist-info/WHEEL
colorex_py-0.1.5.dist-info/RECORD
