Metadata-Version: 2.3
Name: colorex-py
Version: 0.1.5
Summary: colorex-py is a simple and flexible Python Module that provides an easy way to style your terminal output with color and text formatting. With support for both RGB and HEX color codes, as well as text styles like bold, italic, underline, strikethrough, and more, it makes your terminal applications visually more appealing and readable.
Author: LunaStev
Author-email: lunastev@gurmstudios.com
Requires-Python: >=3.5,<4.0
Classifier: Programming Language :: Python :: 3
Classifier: Programming Language :: Python :: 3.5
Classifier: Programming Language :: Python :: 3.6
Classifier: Programming Language :: Python :: 3.7
Classifier: Programming Language :: Python :: 3.8
Classifier: Programming Language :: Python :: 3.9
Classifier: Programming Language :: Python :: 3.10
Classifier: Programming Language :: Python :: 3.11
Classifier: Programming Language :: Python :: 3.12
Classifier: Programming Language :: Python :: 3.13
